{
  "features": [
    {
      "id": "mt-alps",
      "name": { "en": "Alps", "zh": "阿尔卑斯山脉" },
      "type": "mountain",
      "coordinates": [10.0, 46.5],
      "path": [[6.36, 44.92], [6.87, 45.83], [7.66, 45.98], [8.0, 46.5], [9.91, 46.38], [12.69, 47.07], [13.84, 46.38], [15.5, 46.5]],
      "icon": "⛰️"
    },
    {
      "id": "mt-pyrenees",
      "name": { "en": "Pyrenees", "zh": "比利牛斯山脉" },
      "type": "mountain",
      "coordinates": [0.66, 42.63],
      "path": [[-1.8, 43.3], [-0.5, 42.8], [0.66, 42.63], [2.0, 42.5], [3.2, 42.4]],
      "icon": "⛰️"
    },
    {
      "id": "mt-carpathians",
      "name": { "en": "Carpathians", "zh": "喀尔巴阡山脉" },
      "type": "mountain",
      "coordinates": [24.0, 47.0],
      "path": [[18.0, 49.5], [20.1, 49.2], [24.0, 47.5], [26.5, 46.5], [25.0, 45.5], [22.5, 44.5]],
      "icon": "⛰️"
    },
    {
      "id": "mt-apennines",
      "name": { "en": "Apennines", "zh": "亚平宁山脉" },
      "type": "mountain",
      "coordinates": [13.5, 42.5],
      "path": [[9.0, 44.5], [11.0, 44.0], [13.5, 42.5], [15.5, 40.5], [16.5, 38.5]],
      "icon": "⛰️"
    },
    {
      "id": "mt-caucasus",
      "name": { "en": "Caucasus", "zh": "高加索山脉" },
      "type": "mountain",
      "coordinates": [42.4, 43.3],
      "path": [[37.0, 44.8], [39.5, 44.0], [42.4, 43.3], [45.0, 42.0], [48.0, 41.0]],
      "icon": "⛰️"
    },
    {
      "id": "mt-scandinavian",
      "name": { "en": "Scandinavian Mountains", "zh": "斯堪的纳维亚山脉" },
      "type": "mountain",
      "coordinates": [14.0, 64.0],
      "path": [[7.0, 59.5], [8.3, 61.6], [14.0, 64.0], [18.0, 68.0], [22.0, 69.5]],
      "icon": "⛰️"
    },
    {
      "id": "mt-dinaric",
      "name": { "en": "Dinaric Alps", "zh": "迪纳拉山脉" },
      "type": "mountain",
      "coordinates": [17.0, 44.0],
      "path": [[14.5, 45.5], [17.0, 44.0], [19.0, 43.0], [21.0, 42.0]],
      "icon": "⛰️"
    },
    {
      "id": "rv-danube",
      "name": { "en": "Danube", "zh": "多瑙河" },
      "type": "river",
      "coordinates": [19.0, 47.5],
      "path": [[8.50, 47.95], [9.99, 48.40], [12.10, 49.02], [13.43, 48.57], [14.29, 48.31], [16.37, 48.21], [17.11, 48.15], [19.04, 47.50], [20.46, 44.81], [25.95, 43.85], [28.05, 45.44], [29.65, 45.16]],
      "icon": "🌊"
    },
    {
      "id": "rv-rhine",
      "name": { "en": "Rhine", "zh": "莱茵河" },
      "type": "river",
      "coordinates": [7.6, 50.3],
      "path": [[8.67, 46.66], [9.53, 46.85], [9.18, 47.66], [7.59, 47.56], [7.75, 48.57], [7.59, 50.36], [6.96, 50.94], [6.77, 51.23], [4.48, 51.92]],
      "icon": "🌊"
    },
    {
      "id": "rv-volga",
      "name": { "en": "Volga", "zh": "伏尔加河" },
      "type": "river",
      "coordinates": [48.5, 52.0],
      "path": [[32.47, 57.25], [35.90, 56.86], [39.89, 57.63], [44.01, 56.33], [49.11, 55.79], [50.12, 53.18], [44.51, 48.71], [48.04, 46.35]],
      "icon": "🌊"
    },
    {
      "id": "rv-rhone",
      "name": { "en": "Rhone", "zh": "罗讷河" },
      "type": "river",
      "coordinates": [4.8, 45.0],
      "path": [[7.98, 46.32], [7.37, 46.23], [6.14, 46.20], [4.84, 45.76], [4.81, 43.95], [4.63, 43.68]],
      "icon": "🌊"
    },
    {
      "id": "rv-po",
      "name": { "en": "Po", "zh": "波河" },
      "type": "river",
      "coordinates": [10.0, 45.0],
      "path": [[7.10, 44.70], [7.69, 45.07], [9.69, 45.05], [10.02, 45.13], [11.62, 44.84], [12.42, 44.97]],
      "icon": "🌊"
    },
    {
      "id": "rv-loire",
      "name": { "en": "Loire", "zh": "卢瓦尔河" },
      "type": "river",
      "coordinates": [2.0, 47.5],
      "path": [[3.88, 45.04], [4.07, 46.04], [3.16, 46.99], [1.91, 47.90], [0.68, 47.39], [-1.55, 47.22], [-2.21, 47.27]],
      "icon": "🌊"
    },
    {
      "id": "rv-tagus",
      "name": { "en": "Tagus", "zh": "塔霍河" },
      "type": "river",
      "coordinates": [-4.0, 39.8],
      "path": [[-1.68, 40.32], [-3.60, 40.03], [-4.03, 39.86], [-6.89, 39.72], [-8.69, 39.24], [-9.14, 38.72]],
      "icon": "🌊"
    },
    {
      "id": "rv-elbe",
      "name": { "en": "Elbe", "zh": "易北河" },
      "type": "river",
      "coordinates": [12.0, 52.0],
      "path": [[15.54, 50.78], [13.74, 51.05], [11.63, 52.12], [9.99, 53.55]],
      "icon": "🌊"
    },
    {
      "id": "rv-vistula",
      "name": { "en": "Vistula", "zh": "维斯瓦河" },
      "type": "river",
      "coordinates": [21.0, 52.2],
      "path": [[19.00, 49.62], [19.95, 50.06], [21.01, 52.23], [18.65, 54.35]],
      "icon": "🌊"
    },
    {
      "id": "rv-dnieper",
      "name": { "en": "Dnieper", "zh": "第聂伯河" },
      "type": "river",
      "coordinates": [31.0, 48.0],
      "path": [[33.72, 55.87], [30.52, 50.45], [35.05, 48.46], [32.62, 46.64]],
      "icon": "🌊"
    }
  ]
}
